py_shopify_graphql/__init__.py
py_shopify_graphql/client.py
py_shopify_graphql/exceptions.py
py_shopify_graphql-0.1.1.dist-info/METADATA
py_shopify_graphql-0.1.1.dist-info/WHEEL
py_shopify_graphql-0.1.1.dist-info/top_level.txt
py_shopify_graphql-0.1.1.dist-info/RECORD
